labelu/__init__.py
labelu/alembic_labelu/__init__.py
labelu/alembic_labelu/alembic.ini
labelu/alembic_labelu/alembic_labelu_tools.py
labelu/alembic_labelu/env.py
labelu/alembic_labelu/run_migrate.py
labelu/alembic_labelu/script.py.mako
labelu/alembic_labelu/versions/0145db0fec34_change_result_format.py
labelu/alembic_labelu/versions/034c7045b540_remove_task_attachment_ids.py
labelu/alembic_labelu/versions/1b174ca5159a_update_fields.py
labelu/alembic_labelu/versions/2eb983c9a254_add_collaborators_and_updaters.py
labelu/alembic_labelu/versions/363f9eea797e_change_tool_config_format.py
labelu/alembic_labelu/versions/54fee6a7ecd8_init_db.py
labelu/alembic_labelu/versions/9d5da133bbe4_replace_key_with_value_in_sample_table.py
labelu/alembic_labelu/versions/bc8fcb35b66b_add_media_and_pre_annotation.py
labelu/alembic_labelu/versions/e76c2ca5562e_add_inner_id.py
labelu/alembic_labelu/versions/eb9c5b98168b_add_sample_name_and_data_to_task_pre_.py
labelu/internal/__init__.py
labelu/internal/adapter/__init__.py
labelu/internal/adapter/persistence/crud_attachment.py
labelu/internal/adapter/persistence/crud_pre_annotation.py
labelu/internal/adapter/persistence/crud_sample.py
labelu/internal/adapter/persistence/crud_task.py
labelu/internal/adapter/persistence/crud_user.py
labelu/internal/adapter/routers/__init__.py
labelu/internal/adapter/routers/attachment.py
labelu/internal/adapter/routers/pre_annotation.py
labelu/internal/adapter/routers/sample.py
labelu/internal/adapter/routers/task.py
labelu/internal/adapter/routers/user.py
labelu/internal/adapter/ws/__init__.py
labelu/internal/adapter/ws/sample.py
labelu/internal/application/__init__.py
labelu/internal/application/command/__init__.py
labelu/internal/application/command/attachment.py
labelu/internal/application/command/pre_annotation.py
labelu/internal/application/command/sample.py
labelu/internal/application/command/task.py
labelu/internal/application/command/user.py
labelu/internal/application/response/__init__.py
labelu-1.3.2.dist-info/entry_points.txt
labelu-1.3.2.dist-info/LICENSE
labelu-1.3.2.dist-info/WHEEL
labelu-1.3.2.dist-info/METADATA
labelu-1.3.2.dist-info/RECORD
