Metadata-Version: 2.1
Name: labelu
Version: 1.3.2
Summary: 
Home-page: https://github.com/opendatalab/labelU
License: Apache-2.0
Author: shenguanlin
Author-email: shenguanlin@pjlab.org.cn
Requires-Python: >=3.11,<4.0
Classifier: License :: OSI Approved :: Apache Software License
Classifier: Programming Language :: Python :: 3
Classifier: Programming Language :: Python :: 3.11
Provides-Extra: mysql
Requires-Dist: aiofiles (>=22.1.0,<23.0.0)
Requires-Dist: alembic (>=1.9.4,<2.0.0)
Requires-Dist: appdirs (>=1.4.4,<2.0.0)
Requires-Dist: bcrypt (==4.3.0)
Requires-Dist: email-validator (>=1.3.0,<2.0.0)
Requires-Dist: fastapi (>=0.90.0,<0.91.0)
Requires-Dist: httpx (>=0.27.0,<0.28.0)
Requires-Dist: loguru (>=0.6.0,<0.7.0)
Requires-Dist: mysqlclient (>=2.1.1,<3.0.0); extra == "mysql"
Requires-Dist: passlib[bcrypt] (>=1.7.4,<2.0.0)
Requires-Dist: pillow (>=9.3.0,<10.0.0)
Requires-Dist: python-dotenv (>=0.21.0,<0.22.0)
Requires-Dist: python-jose[cryptography] (>=3.3.0,<4.0.0)
Requires-Dist: python-multipart (>=0.0.5,<0.0.6)
Requires-Dist: sqlalchemy (>=1.4.43,<2.0.0)
Requires-Dist: tfrecord (>=1.14.5,<2.0.0)
Requires-Dist: typer[all] (>=0.7.0,<0.8.0)
Requires-Dist: uvicorn (>=0.19.0,<0.20.0)
Requires-Dist: websockets (>=10.0.0,<11.0.0)
Project-URL: Repository, https://github.com/opendatalab/labelU
